mypublicip/__init__.py
mypublicip-1.0.3.dist-info/LICENSE
mypublicip-1.0.3.dist-info/METADATA
mypublicip-1.0.3.dist-info/WHEEL
mypublicip-1.0.3.dist-info/top_level.txt
mypublicip-1.0.3.dist-info/RECORD
